userexit.py
userexit-0.2.dist-info/DESCRIPTION.rst
userexit-0.2.dist-info/METADATA
userexit-0.2.dist-info/RECORD
userexit-0.2.dist-info/WHEEL
userexit-0.2.dist-info/metadata.json
userexit-0.2.dist-info/top_level.txt
